certbot_dns_gcore/__init__.py
certbot_dns_gcore/__version__.py
certbot_dns_gcore/api_gcore.py
certbot_dns_gcore/dns_gcore.py
tests/__init__.py
tests/conftest.py
tests/test_dns_gcore.py
certbot_dns_gcore-0.1.8.dist-info/METADATA
certbot_dns_gcore-0.1.8.dist-info/WHEEL
certbot_dns_gcore-0.1.8.dist-info/entry_points.txt
certbot_dns_gcore-0.1.8.dist-info/top_level.txt
certbot_dns_gcore-0.1.8.dist-info/RECORD
