Metadata-Version: 2.1
Name: certbot-dns-gcore
Version: 0.1.8
Summary: G-Core DNS Authenticator plugin for Certbot
Home-page: https://github.com/G-Core/gcore-dns-certbot-plugin
Author: G-Core Labs
Author-email: support@gcorelabs.com
License: Apache License 2.0
Requires-Python: >=3.8
Requires-Dist: certbot (>=1.23.0)
Requires-Dist: setuptools (>=39.0.1)
Provides-Extra: docs
Requires-Dist: Sphinx (>=1.0) ; extra == 'docs'
Requires-Dist: sphinx-rtd-theme ; extra == 'docs'
